[
  {
    "UserId": 1,
    "name": "Pensil",
    "description": "Alat untuk menulis",
    "image": "",
    "quantity": 1,
    "location": "tepak alat tulis",
    "condition": "new",
    "isFavorite": true
  },
  {
    "UserId": 1,
    "name": "Penghapus",
    "description": "Alat untuk menghapus",
    "image": "",
    "quantity": 2,
    "location": "tepak alat tulis",
    "condition": "new",
    "isFavorite": false
  },
  {
    "UserId": 1,
    "name": "Penggaris",
    "description": "Alat untuk menggaris",
    "image": "",
    "quantity": 1,
    "location": "tepak alat tulis",
    "condition": "old",
    "isFavorite": false
  }
]